holfuy/__init__.py
holfuy/const.py
holfuy/test_holfuy.py
pyholfuy-0.2.dist-info/licenses/LICENSE
pyholfuy-0.2.dist-info/METADATA
pyholfuy-0.2.dist-info/WHEEL
pyholfuy-0.2.dist-info/top_level.txt
pyholfuy-0.2.dist-info/RECORD
