Metadata-Version: 2.4
Name: pyholfuy
Version: 0.2
Summary: A Python library for interacting with Holfuy weather stations.
Author-email: Håvard Dagenborg <haavardj@dagenborg.net>
License-Expression: MIT
Project-URL: homepage, https://github.com/haavardj/PyHolfuy
Keywords: weather,holfuy,api,python
Classifier: Programming Language :: Python :: 3
Classifier: Operating System :: OS Independent
Requires-Python: >=3.11
License-File: LICENSE
Requires-Dist: aiohttp>=3.9.4
Provides-Extra: test
Requires-Dist: aioresponses==0.7.8; extra == "test"
Requires-Dist: coverage==7.8.0; extra == "test"
Requires-Dist: mypy==1.15.0; extra == "test"
Provides-Extra: dev
Dynamic: license-file
